deploy/__init__.py
deploy/copy_package.py
deploy/download_looq_dependencies.py
deploy/upload_to_s3.py
looqbox/__init__.py
looqbox/global_calling.py
looqbox/json_encoder.py
looqbox/teste.py
looqbox/class_loader/__init__.py
looqbox/class_loader/class_loader.py
looqbox/class_loader/lazy_import.py
looqbox/class_loader/lazy_load.py
looqbox/class_loader/tests/__init__.py
looqbox/class_loader/tests/test_lazy_load.py
looqbox/config/__init__.py
looqbox/config/config_reader.py
looqbox/config/logger.py
looqbox/config/object_mapper.py
looqbox/config/pydantic_configuration.py
looqbox/configuration/LooqObjects_path.json
looqbox/configuration/__init__.py
looqbox/configuration/connection_class_path.json
looqbox/configuration/database_connection_settings.json
looqbox/configuration/default_style.json
looqbox/configuration/flow_setting.json
looqbox/configuration/timeout_settings_class_path.json
looqbox/configuration/popo/__init__.py
looqbox/configuration/popo/database_connection.py
looqbox/configuration/popo/flow_settings.py
looqbox/configuration/popo/response_package_configurations.py
looqbox/database/__init__.py
looqbox/database/database_exceptions.py
looqbox/database/database_functions.py
looqbox/database/query_log.py
looqbox/database/query_metrics.py
looqbox/database/query_setting.py
looqbox/database/connections/__init__.py
looqbox/database/connections/api.py
looqbox/database/connections/connection_base.py
looqbox/database/connections/connection_big_query.py
looqbox/database/connections/connection_jdbc_query_caller.py
looqbox/database/connections/connection_jdbc_query_executor.py
looqbox/database/connections/connection_mongo.py
looqbox/database/connections/sql_thread_manager.py
looqbox/database/connections/jars/QueryCaller.jar
looqbox/database/connections/jars/__init__.py
looqbox/database/test/__init__.py
looqbox/database/test/test_connection_big_query.py
looqbox/database/test/test_connection_query_caller.py
looqbox/database/test/test_connection_query_executor.py
looqbox-6.2.8.dist-info/LICENSE
looqbox-6.2.8.dist-info/METADATA
looqbox-6.2.8.dist-info/WHEEL
looqbox-6.2.8.dist-info/top_level.txt
looqbox-6.2.8.dist-info/RECORD
