Metadata-Version: 2.2
Name: looqbox
Version: 6.2.8
Summary: A looqbox package to write python scripts in the platform
Home-page: https://github.com/looqbox/python-package
Author: looqbox
Author-email: admin@looqbox.com
Classifier: Programming Language :: Python :: 3
Classifier: License :: OSI Approved :: MIT License
Classifier: Operating System :: OS Independent
License-File: LICENSE
Requires-Dist: setuptools
Requires-Dist: packaging
Requires-Dist: aiohttp
Requires-Dist: dnspython
Requires-Dist: certifi
Requires-Dist: aiohttp==3.9.2
Requires-Dist: dnspython==2.2.1
Requires-Dist: certifi==2023.7.22
Requires-Dist: multimethod
Requires-Dist: multipledispatch
Requires-Dist: numpy
Requires-Dist: pandas
Requires-Dist: pandas-datareader
Requires-Dist: plotly
Requires-Dist: pydantic
Requires-Dist: pydantic_core
Requires-Dist: pymongo
Requires-Dist: requests
Requires-Dist: google-api-core
Requires-Dist: google-api-python-client
Requires-Dist: google-auth
Requires-Dist: google-auth-httplib2
Requires-Dist: google-auth-oauthlib
Requires-Dist: google-cloud
Requires-Dist: google-cloud-bigquery
Requires-Dist: google-cloud-bigquery-storage
Requires-Dist: google-cloud-core
Requires-Dist: google-crc32c
Requires-Dist: google-resumable-media
Requires-Dist: googleapis-common-protos
Requires-Dist: reportlab==3.6.12
Requires-Dist: beautifulsoup4==4.11.1
Requires-Dist: kaleido==0.2.1
Requires-Dist: boto3==1.24.79
Requires-Dist: botocore==1.27.79
Dynamic: author
Dynamic: author-email
Dynamic: classifier
Dynamic: home-page
Dynamic: requires-dist
Dynamic: summary
